{
    "version": "2.107.0-beta.19",
    "description": "Supabase CLI",
    "homepage": "https://supabase.com/",
    "license": "MIT",
    "architecture": {
        "64bit": {
            "url": "https://github.com/supabase/cli/releases/download/v2.107.0-beta.19/supabase_windows_amd64.tar.gz",
            "hash": "03c4263efcd2566bd26e77e37c2503c6c4555def1ffcf74fc56f8afb9d6628cd"
        },
        "arm64": {
            "url": "https://github.com/supabase/cli/releases/download/v2.107.0-beta.19/supabase_windows_arm64.tar.gz",
            "hash": "912309d2bfbb880bb0b3811f3906bc3c40183ab6d11aefd70dc4865bca1fe2eb"
        }
    },
    "bin": "supabase.exe",
    "checkver": {
        "github": "https://github.com/supabase/cli"
    },
    "autoupdate": {
        "architecture": {
            "64bit": {
                "url": "https://github.com/supabase/cli/releases/download/v$version/supabase_windows_amd64.tar.gz"
            },
            "arm64": {
                "url": "https://github.com/supabase/cli/releases/download/v$version/supabase_windows_arm64.tar.gz"
            }
        },
        "hash": {
            "url": "$baseurl/supabase_$version_checksums.txt"
        }
    }
}
