{
    "version": "1.163.0",
    "architecture": {
        "64bit": {
            "url": "https://github.com/supabase/cli/releases/download/v1.163.0/supabase_windows_amd64.tar.gz",
            "bin": [
                "supabase.exe"
            ],
            "hash": "c8ab563855d70b6ba84f874f326530e411a3fc1c44e0a460202181d8faffa65d"
        },
        "arm64": {
            "url": "https://github.com/supabase/cli/releases/download/v1.163.0/supabase_windows_arm64.tar.gz",
            "bin": [
                "supabase.exe"
            ],
            "hash": "ef796f1f3a2f6ce1034e4729f58a364aac94109c1d9660c58b3d46579e3d0376"
        }
    },
    "homepage": "https://supabase.com",
    "license": "MIT",
    "description": "Supabase CLI (Beta)"
}
