{
    "version": "2.13.8",
    "architecture": {
        "64bit": {
            "url": "https://github.com/supabase/cli/releases/download/v2.13.8/supabase_windows_amd64.tar.gz",
            "bin": [
                "supabase.exe"
            ],
            "hash": "5d51c4d75ddc374c0ff02b89cbbfc52769659808beeb178b43d3da8c1715c2df"
        },
        "arm64": {
            "url": "https://github.com/supabase/cli/releases/download/v2.13.8/supabase_windows_arm64.tar.gz",
            "bin": [
                "supabase.exe"
            ],
            "hash": "ff7e764b0b51f2961daec4f5710ec8a781ac0a574fc31f6497b509b7a61ef28c"
        }
    },
    "homepage": "https://supabase.com",
    "license": "MIT",
    "description": "Supabase CLI (Beta)"
}
