{
    "version": "2.59.6",
    "architecture": {
        "64bit": {
            "url": "https://github.com/supabase/cli/releases/download/v2.59.6/supabase_windows_amd64.tar.gz",
            "bin": [
                "supabase.exe"
            ],
            "hash": "1cfe7c346e0f5e4a2436315afe6bc443a9f4ba94f86fcff2b206f786b3b18899"
        },
        "arm64": {
            "url": "https://github.com/supabase/cli/releases/download/v2.59.6/supabase_windows_arm64.tar.gz",
            "bin": [
                "supabase.exe"
            ],
            "hash": "ed5badbb05733d72665af7f7738462622818477104c8d742d0c45ea3bcbbe04a"
        }
    },
    "homepage": "https://supabase.com",
    "license": "MIT",
    "description": "Supabase CLI (Beta)"
}
