{
    "version": "2.20.1",
    "architecture": {
        "64bit": {
            "url": "https://github.com/supabase/cli/releases/download/v2.20.1/supabase_windows_amd64.tar.gz",
            "bin": [
                "supabase.exe"
            ],
            "hash": "8e1549f8ea99d5127e8debd740a1b5bb7585a42df3bddda2b11c3db2acbf9f25"
        },
        "arm64": {
            "url": "https://github.com/supabase/cli/releases/download/v2.20.1/supabase_windows_arm64.tar.gz",
            "bin": [
                "supabase.exe"
            ],
            "hash": "7d65516e6f1f014909c2e7782a3ef4e17f73386702ba1f04162b640ce5e2a09a"
        }
    },
    "homepage": "https://supabase.com",
    "license": "MIT",
    "description": "Supabase CLI (Beta)"
}
