{
    "version": "1.182.0",
    "architecture": {
        "64bit": {
            "url": "https://github.com/supabase/cli/releases/download/v1.182.0/supabase_windows_amd64.tar.gz",
            "bin": [
                "supabase.exe"
            ],
            "hash": "2376466637a29b83e4c7c7727309519f58464680f07dc934ba612d1a9f83380d"
        },
        "arm64": {
            "url": "https://github.com/supabase/cli/releases/download/v1.182.0/supabase_windows_arm64.tar.gz",
            "bin": [
                "supabase.exe"
            ],
            "hash": "e4ffc596c41c29ba04bab287dff5ee72dc0ce0f8f24c4876fdfb024972f0e569"
        }
    },
    "homepage": "https://supabase.com",
    "license": "MIT",
    "description": "Supabase CLI (Beta)"
}
