{
    "version": "2.110.0-beta.8",
    "description": "Supabase CLI",
    "homepage": "https://supabase.com/",
    "license": "MIT",
    "architecture": {
        "64bit": {
            "url": "https://github.com/supabase/cli/releases/download/v2.110.0-beta.8/supabase_windows_amd64.tar.gz",
            "hash": "cf5e29bc4f4877351a76b2bc773c608e1c47fc0df38d7f00c243cdf4c953ec31"
        },
        "arm64": {
            "url": "https://github.com/supabase/cli/releases/download/v2.110.0-beta.8/supabase_windows_arm64.tar.gz",
            "hash": "d96928e5f7b03595ee17fae9db7725fd7405c420f43d2039bedcb63ca49f77f2"
        }
    },
    "bin": "supabase.exe",
    "checkver": {
        "github": "https://github.com/supabase/cli"
    },
    "autoupdate": {
        "architecture": {
            "64bit": {
                "url": "https://github.com/supabase/cli/releases/download/v$version/supabase_windows_amd64.tar.gz"
            },
            "arm64": {
                "url": "https://github.com/supabase/cli/releases/download/v$version/supabase_windows_arm64.tar.gz"
            }
        },
        "hash": {
            "url": "$baseurl/supabase_$version_checksums.txt"
        }
    }
}
