{
    "version": "2.41.3",
    "architecture": {
        "64bit": {
            "url": "https://github.com/supabase/cli/releases/download/v2.41.3/supabase_windows_amd64.tar.gz",
            "bin": [
                "supabase.exe"
            ],
            "hash": "b2839b36f32f0da9b783abc27d52290ddd95a3b9439555e4fa8b047304120136"
        },
        "arm64": {
            "url": "https://github.com/supabase/cli/releases/download/v2.41.3/supabase_windows_arm64.tar.gz",
            "bin": [
                "supabase.exe"
            ],
            "hash": "eeee362e59123d9c525654c839827af63db01729dd0ad002a3e69301a71c40ba"
        }
    },
    "homepage": "https://supabase.com",
    "license": "MIT",
    "description": "Supabase CLI (Beta)"
}
